opentelemetry/instrumentation/asyncclick/__init__.py
opentelemetry/instrumentation/asyncclick/package.py
opentelemetry/instrumentation/asyncclick/py.typed
opentelemetry/instrumentation/asyncclick/version.py
opentelemetry_instrumentation_asyncclick-0.60b1.dist-info/METADATA
opentelemetry_instrumentation_asyncclick-0.60b1.dist-info/WHEEL
opentelemetry_instrumentation_asyncclick-0.60b1.dist-info/entry_points.txt
opentelemetry_instrumentation_asyncclick-0.60b1.dist-info/RECORD
